langchain_apiverve/__init__.py
langchain_apiverve/client.py
langchain_apiverve/schemas.py
langchain_apiverve/toolkit.py
langchain_apiverve/tools.py
langchain_apiverve/utils.py
langchain_apiverve-0.1.0.dist-info/licenses/LICENSE
langchain_apiverve-0.1.0.dist-info/METADATA
langchain_apiverve-0.1.0.dist-info/WHEEL
langchain_apiverve-0.1.0.dist-info/RECORD
