Metadata-Version: 2.4
Name: langchain-apiverve
Version: 0.1.0
Summary: LangChain integration for APIVerve - Access 310+ utility APIs for AI agents
License: MIT
License-File: LICENSE
Keywords: langchain,langchain-integration,apiverve,api,ai,llm,agents,tools,validation,utilities
Author: APIVerve
Author-email: hello@apiverve.com
Requires-Python: >=3.9
Classifier: Development Status :: 4 - Beta
Classifier: Intended Audience :: Developers
Classifier: License :: OSI Approved :: MIT License
Classifier: Operating System :: OS Independent
Classifier: Programming Language :: Python :: 3
Classifier: Programming Language :: Python :: 3.9
Classifier: Programming Language :: Python :: 3.10
Classifier: Programming Language :: Python :: 3.11
Classifier: Programming Language :: Python :: 3.12
Classifier: Topic :: Scientific/Engineering :: Artificial Intelligence
Classifier: Topic :: Software Development :: Libraries :: Python Modules
Provides-Extra: dev
Requires-Dist: langchain-core (>=0.2.0)
Requires-Dist: mypy (>=1.0.0) ; extra == "dev"
Requires-Dist: pydantic (>=2.0.0)
Requires-Dist: pytest (>=7.0.0) ; extra == "dev"
Requires-Dist: pytest-asyncio (>=0.21.0) ; extra == "dev"
Requires-Dist: requests (>=2.28.0)
Requires-Dist: ruff (>=0.1.0) ; extra == "dev"
Project-URL: Changelog, https://github.com/apiverve/langchain-apiverve/releases
Project-URL: Documentation, https://docs.apiverve.com
Project-URL: Homepage, https://apiverve.com
Project-URL: Issues, https://github.com/apiverve/langchain-apiverve/issues
Project-URL: Repository, https://github.com/apiverve/langchain-apiverve
